alertlvm/__init__.py
alertlvm/lvm.py
alert_lvm-1.1.0.dist-info/LICENSE
alert_lvm-1.1.0.dist-info/METADATA
alert_lvm-1.1.0.dist-info/WHEEL
alert_lvm-1.1.0.dist-info/top_level.txt
alert_lvm-1.1.0.dist-info/RECORD
