Metadata-Version: 2.1
Name: alert-lvm
Version: 1.1.0
Summary: A client library to call the LVM API with some helpful functions
Author-email: "intellicloud.ai" <xbrain_lvm@intellicloud.ai>
License: Copyright (c) 2018 The Python Packaging Authority
Project-URL: Homepage, https://intellicloudai.com
Classifier: License :: OSI Approved :: MIT License
Classifier: Programming Language :: Python :: 3
Requires-Python: >=3.9
License-File: LICENSE
Requires-Dist: requests
Requires-Dist: opencv-python
Provides-Extra: dev
Requires-Dist: black ; extra == 'dev'
Requires-Dist: bumpver ; extra == 'dev'
Requires-Dist: isort ; extra == 'dev'
Requires-Dist: pip-tools ; extra == 'dev'
Requires-Dist: pytest ; extra == 'dev'
